playing/Direct.py
playing/__init__.py
playgrounds-0.0.1.dist-info/LICENSE
playgrounds-0.0.1.dist-info/METADATA
playgrounds-0.0.1.dist-info/WHEEL
playgrounds-0.0.1.dist-info/top_level.txt
playgrounds-0.0.1.dist-info/RECORD
